mousetrap/__init__.py
mousetrap/mousetrap.py
mousetrap-3.0.5.dist-info/METADATA
mousetrap-3.0.5.dist-info/RECORD
mousetrap-3.0.5.dist-info/WHEEL
mousetrap-3.0.5.dist-info/entry_points.txt
mousetrap-3.0.5.dist-info/top_level.txt
