Metadata-Version: 2.1
Name: mousetrap
Version: 3.0.5
Summary: An X11 utility that hides the mouse pointer after a specified interval of time
Home-page: https://github.com/eazar001/mousetrap
Author: Ebrahim Azarisooreh
Author-email: ebrahim.azarisooreh@gmail.com
License: MIT
Keywords: hide mouse cursor pointer x11 xlib
Platform: UNKNOWN
Classifier: Development Status :: 5 - Production/Stable
Classifier: Environment :: X11 Applications
Classifier: Intended Audience :: End Users/Desktop
Classifier: License :: OSI Approved :: MIT License
Classifier: Operating System :: Unix
Classifier: Topic :: Utilities
Requires-Dist: python-xlib
